bandecoapi/__init__.py
bandecoapi/api/__init__.py
bandecoapi/api/api.py
bandecoapi/cardapio/__init__.py
bandecoapi/cardapio/cardapio.py
bandecoapi-0.2.dist-info/DESCRIPTION.rst
bandecoapi-0.2.dist-info/METADATA
bandecoapi-0.2.dist-info/RECORD
bandecoapi-0.2.dist-info/WHEEL
bandecoapi-0.2.dist-info/metadata.json
bandecoapi-0.2.dist-info/top_level.txt
