Metadata-Version: 2.0
Name: bandecoapi
Version: 0.2
Summary: API to get menus from Unicamp's bandeco
Home-page: https://github.com/Maronato/BandecoAPI
Author: Gustavo Maronato
Author-email: gustavomaronato@gmail.com
License: MIT
Keywords: api bandeco unicamp
Platform: UNKNOWN
Classifier: Development Status :: 3 - Alpha
Classifier: Intended Audience :: Developers
Classifier: Topic :: Software Development :: Build Tools
Classifier: License :: OSI Approved :: MIT License
Classifier: Programming Language :: Python :: 3
Classifier: Programming Language :: Python :: 3.3
Classifier: Programming Language :: Python :: 3.4
Classifier: Programming Language :: Python :: 3.5
Requires-Dist: beautifulsoup4 (==4.6.0)
Requires-Dist: requests (==2.13.0)
